odoo9_addon_connector_prestashop_catalog_manager-9.0.1.0.3-py2.7-nspkg.pth
odoo9_addon_connector_prestashop_catalog_manager-9.0.1.0.3.dist-info/DESCRIPTION.rst
odoo9_addon_connector_prestashop_catalog_manager-9.0.1.0.3.dist-info/METADATA
odoo9_addon_connector_prestashop_catalog_manager-9.0.1.0.3.dist-info/RECORD
odoo9_addon_connector_prestashop_catalog_manager-9.0.1.0.3.dist-info/WHEEL
odoo9_addon_connector_prestashop_catalog_manager-9.0.1.0.3.dist-info/metadata.json
odoo9_addon_connector_prestashop_catalog_manager-9.0.1.0.3.dist-info/namespace_packages.txt
odoo9_addon_connector_prestashop_catalog_manager-9.0.1.0.3.dist-info/top_level.txt
odoo_addons/connector_prestashop_catalog_manager/README.rst
odoo_addons/connector_prestashop_catalog_manager/__init__.py
odoo_addons/connector_prestashop_catalog_manager/__openerp__.py
odoo_addons/connector_prestashop_catalog_manager/consumer.py
odoo_addons/connector_prestashop_catalog_manager/models/__init__.py
odoo_addons/connector_prestashop_catalog_manager/models/product_category/__init__.py
odoo_addons/connector_prestashop_catalog_manager/models/product_category/exporter.py
odoo_addons/connector_prestashop_catalog_manager/models/product_image/__init__.py
odoo_addons/connector_prestashop_catalog_manager/models/product_image/exporter.py
odoo_addons/connector_prestashop_catalog_manager/models/product_product/__init__.py
odoo_addons/connector_prestashop_catalog_manager/models/product_product/common.py
odoo_addons/connector_prestashop_catalog_manager/models/product_product/exporter.py
odoo_addons/connector_prestashop_catalog_manager/models/product_template/__init__.py
odoo_addons/connector_prestashop_catalog_manager/models/product_template/common.py
odoo_addons/connector_prestashop_catalog_manager/models/product_template/exporter.py
odoo_addons/connector_prestashop_catalog_manager/static/description/icon.png
odoo_addons/connector_prestashop_catalog_manager/static/description/icon.svg
odoo_addons/connector_prestashop_catalog_manager/views/product_attribute_view.xml
odoo_addons/connector_prestashop_catalog_manager/views/product_image_view.xml
odoo_addons/connector_prestashop_catalog_manager/views/product_view.xml
odoo_addons/connector_prestashop_catalog_manager/wizards/__init__.py
odoo_addons/connector_prestashop_catalog_manager/wizards/active_deactive_products.py
odoo_addons/connector_prestashop_catalog_manager/wizards/active_deactive_products_view.xml
odoo_addons/connector_prestashop_catalog_manager/wizards/export_category.py
